setup.py
version.py
version.egg-info/PKG-INFO
version.egg-info/SOURCES.txt
version.egg-info/dependency_links.txt
version.egg-info/top_level.txt